setup.py
lyx/__init__.py
lyx/dataclean.py
lyx/io.py
lyx/leetcode.py
lyx/threads.py
lyx/tools.py
lyx.egg-info/PKG-INFO
lyx.egg-info/SOURCES.txt
lyx.egg-info/dependency_links.txt
lyx.egg-info/requires.txt
lyx.egg-info/top_level.txt