Metadata-Version: 1.2
Name: lyx
Version: 0.7.2
Summary: python toolbox created by kashimotoxiang
Home-page: https://github.com/kashimotoxiang/lyx_lib
Author: kashimotoxiang
Author-email: kashimotoxiang@gmail.com
Maintainer: kashimotoxiang
Maintainer-email: kashimotoxiang@gmail.com
License: MIT
Platform: all
Classifier: Development Status :: 3 - Alpha
Classifier: Intended Audience :: Developers
Classifier: Topic :: Software Development :: Build Tools
Classifier: License :: OSI Approved :: MIT License
Classifier: Programming Language :: Python :: 3
Requires-Python: >=3.7
